{
  "highlight": {
    "brand-background": {
      "value": "hsl({color.brand.100})",
      "attributes": {
        "category": "color"
      }
    },
    "brand-foreground": {
      "value": "hsl(246 100% 72%)",
      "attributes": {
        "category": "color"
      }
    },
    "gray-background": {
      "value": "hsl({color.primary.80})",
      "attributes": {
        "category": "color"
      }
    },
    "gray-foreground": {
      "value": "hsl({color.primary.40})",
      "attributes": {
        "category": "color"
      }
    },
    "yellow-background": {
      "value": "hsl({color.yellow.100})",
      "attributes": {
        "category": "color"
      }
    },
    "yellow-foreground": {
      "value": "hsl({color.yellow.40})",
      "attributes": {
        "category": "color"
      }
    },
    "green-background": {
      "value": "hsl({color.green.100})",
      "attributes": {
        "category": "color"
      }
    },
    "green-foreground": {
      "value": "hsl({color.green.40})",
      "attributes": {
        "category": "color"
      }
    },
    "blue-background": {
      "value": "hsl({color.blue.100})",
      "attributes": {
        "category": "color"
      }
    },
    "blue-foreground": {
      "value": "hsl({color.blue.30})",
      "attributes": {
        "category": "color"
      }
    },
    "red-background": {
      "value": "hsl({color.red.100})",
      "attributes": {
        "category": "color"
      }
    },
    "red-foreground": {
      "value": "hsl({color.red.30})",
      "attributes": {
        "category": "color"
      }
    },
    "cyan-background": {
      "value": "hsl({color.cyan.100})",
      "attributes": {
        "category": "color"
      }
    },
    "cyan-foreground": {
      "value": "hsl({color.cyan.40})",
      "attributes": {
        "category": "color"
      }
    },
    "purple-background": {
      "value": "hsl({color.purple.100})",
      "attributes": {
        "category": "color"
      }
    },
    "purple-foreground": {
      "value": "hsl({color.purple.40})",
      "attributes": {
        "category": "color"
      }
    },
    "indigo-background": {
      "value": "hsl({color.indigo.80})",
      "attributes": {
        "category": "color"
      }
    },
    "indigo-foreground": {
      "value": "hsl({color.indigo.30})",
      "attributes": {
        "category": "color"
      }
    },
    "dipsy-background": {
      "value": "hsl({color.dipsy.90})",
      "attributes": {
        "category": "color"
      }
    },
    "dipsy-foreground": {
      "value": "hsl({color.dipsy.40})",
      "attributes": {
        "category": "color"
      }
    },
    "salmon-background": {
      "value": "hsl({color.salmon.90})",
      "attributes": {
        "category": "color"
      }
    },
    "salmon-foreground": {
      "value": "hsl({color.salmon.20})",
      "attributes": {
        "category": "color"
      }
    },
    "magenta-background": {
      "value": "hsl({color.magenta.90})",
      "attributes": {
        "category": "color"
      }
    },
    "magenta-foreground": {
      "value": "hsl({color.magenta.20})",
      "attributes": {
        "category": "color"
      }
    }
  }
}
