{
  "dimmed": {
    "0": {
      "value": "{color.gray.100}",
      "$type": "color"
    },
    "1": {
      "value": "{color.gray.90}",
      "$type": "color"
    },
    "2": {
      "value": "{color.gray.80}",
      "$type": "color"
    },
    "3": {
      "value": "{color.gray.70}",
      "$type": "color"
    },
    "4": {
      "value": "{color.gray.60}",
      "$type": "color"
    },
    "5": {
      "value": "{color.gray.50}",
      "$type": "color"
    },
    "6": {
      "value": "{color.gray.40}",
      "$type": "color"
    },
    "7": {
      "value": "{color.gray.30}",
      "$type": "color"
    },
    "8": {
      "value": "{color.gray.20}",
      "$type": "color"
    }
  }
}
